{
	"id": "6EC3RlZGVb1wymu",
	"json": "{\"id\":\"6EC3RlZGVb1wymu\",\"url\":\"https://pss.bdstatic.com/static/superman/css/ubase_sync-d600f57804.css?v=md5\",\"uniqueKey\":\"https://pss.bdstatic.com/static/superman/css/ubase_sync-d600f57804.css?v=md5\",\"method\":\"GET\",\"noRetry\":false,\"retryCount\":0,\"errorMessages\":[],\"headers\":{},\"userData\":{}}",
	"method": "GET",
	"orderNo": 1748421401557,
	"retryCount": 0,
	"uniqueKey": "https://pss.bdstatic.com/static/superman/css/ubase_sync-d600f57804.css?v=md5",
	"url": "https://pss.bdstatic.com/static/superman/css/ubase_sync-d600f57804.css?v=md5"
}